MANIFEST.in
README.txt
setup.py
docs/HISTORY.txt
docs/affinitic.css
docs/layout.html
src/affinitic/__init__.py
src/affinitic.zamqp.egg-info/PKG-INFO
src/affinitic.zamqp.egg-info/SOURCES.txt
src/affinitic.zamqp.egg-info/dependency_links.txt
src/affinitic.zamqp.egg-info/entry_points.txt
src/affinitic.zamqp.egg-info/namespace_packages.txt
src/affinitic.zamqp.egg-info/not-zip-safe
src/affinitic.zamqp.egg-info/requires.txt
src/affinitic.zamqp.egg-info/top_level.txt
src/affinitic/zamqp/__init__.py
src/affinitic/zamqp/changelog.txt
src/affinitic/zamqp/configure.zcml
src/affinitic/zamqp/connection.py
src/affinitic/zamqp/connection.txt
src/affinitic/zamqp/consumer.py
src/affinitic/zamqp/consumer.txt
src/affinitic/zamqp/consumerset.py
src/affinitic/zamqp/consumerset.txt
src/affinitic/zamqp/error.py
src/affinitic/zamqp/index.txt
src/affinitic/zamqp/interfaces.py
src/affinitic/zamqp/introduction.txt
src/affinitic/zamqp/message.py
src/affinitic/zamqp/message.txt
src/affinitic/zamqp/processor.py
src/affinitic/zamqp/publisher.py
src/affinitic/zamqp/publisher.txt
src/affinitic/zamqp/service.py
src/affinitic/zamqp/service.txt
src/affinitic/zamqp/testing.zcml
src/affinitic/zamqp/transactionmanager.py
src/affinitic/zamqp/zamqp.dia
src/affinitic/zamqp/zamqp.png
src/affinitic/zamqp/tests/__init__.py
src/affinitic/zamqp/tests/connection.txt
src/affinitic/zamqp/tests/consumer.txt
src/affinitic/zamqp/tests/consumerset.txt
src/affinitic/zamqp/tests/message.txt
src/affinitic/zamqp/tests/processor.txt
src/affinitic/zamqp/tests/publisher.txt
src/affinitic/zamqp/tests/service.txt
src/affinitic/zamqp/tests/test_doctest.py
src/affinitic/zamqp/tests/testing.py
src/affinitic/zamqp/tests/testing.zcml