Metadata-Version: 1.0
Name: affinitic.zamqp
Version: 0.4
Summary: AMQP Consumer and publisher integration with Zope
Home-page: http://bitbucket.org/jfroche/affinitic.zamqp
Author: Jean-Francois Roche
Author-email: jfroche@affinitic.be
License: ZPL
Platform: UNKNOWN
Classifier: Operating System :: OS Independent
Classifier: Intended Audience :: Developers
Classifier: Topic :: Communications
Classifier: Topic :: System :: Distributed Computing
Classifier: Programming Language :: Python
